praisonaitest/__init__.py
praisonaitest/test.py
praisonaitest-0.0.1.dist-info/METADATA
praisonaitest-0.0.1.dist-info/WHEEL
praisonaitest-0.0.1.dist-info/top_level.txt
praisonaitest-0.0.1.dist-info/RECORD
