Metadata-Version: 2.4
Name: PraisonAITest
Version: 0.0.1
Summary: A minimal and simple testing framework for Large Language Models (LLMs)
Author: MervinPraison
License-Expression: MIT
Project-URL: Homepage, https://github.com/MervinPraison/PraisonAITest
Project-URL: Bug Tracker, https://github.com/MervinPraison/PraisonAITest/issues
Classifier: Programming Language :: Python :: 3
Classifier: Operating System :: OS Independent
Requires-Python: >=3.8
Requires-Dist: litellm>=1.0.0
Requires-Dist: python-dotenv>=1.0.0
